{
    "cloud": {
        "provider": "aws",
        "version": 1,
        "configure": {
            "cluster_user": "",
            "cluster_size": "small",
            "cluster_type": "compute",
            "region": "us-west-2",
            "placement": "us-west-2a",
            "axsys_node_type": "m3.large",
            "axuser_node_type": "c3.2xlarge",
            "min_node_count": 0,
            "max_node_count": 3,
            "axsys_node_count": 0,
            "node_tiers": "master/applatix/user",
            "ax_vol_size": 100,
            "axuser_on_demand_nodes": 0
        }
    }
}
